empire_platform_api_public_client_legacy/__init__.py
empire_platform_api_public_client_legacy/api_client.py
empire_platform_api_public_client_legacy/api_response.py
empire_platform_api_public_client_legacy/configuration.py
empire_platform_api_public_client_legacy/exceptions.py
empire_platform_api_public_client_legacy/py.typed
empire_platform_api_public_client_legacy/rest.py
empire_platform_api_public_client_legacy/api/__init__.py
empire_platform_api_public_client_legacy/api/allocated_auction_api.py
empire_platform_api_public_client_legacy/api/attachment_api.py
empire_platform_api_public_client_legacy/api/auction_api.py
empire_platform_api_public_client_legacy/api/audit_log_api.py
empire_platform_api_public_client_legacy/api/bidding_configuration_api.py
empire_platform_api_public_client_legacy/api/buy_now_offers_api.py
empire_platform_api_public_client_legacy/api/default_bid_api.py
empire_platform_api_public_client_legacy/api/default_nomination_api.py
empire_platform_api_public_client_legacy/api/finance_api.py
empire_platform_api_public_client_legacy/api/finance_information_api.py
empire_platform_api_public_client_legacy/api/manual_file_upload_api.py
empire_platform_api_public_client_legacy/api/messages_api.py
empire_platform_api_public_client_legacy/api/metadata_api.py
empire_platform_api_public_client_legacy/api/nomination_api.py
empire_platform_api_public_client_legacy/api/organisation_api.py
empire_platform_api_public_client_legacy/api/organisation_document_api.py
empire_platform_api_public_client_legacy/api/participant_dashboard_api.py
empire_platform_api_public_client_legacy/api/participant_overview_api.py
empire_platform_api_public_client_legacy/api/profile_api.py
empire_platform_api_public_client_legacy/api/public_allocated_auction_api.py
empire_platform_api_public_client_legacy/api/public_auction_api.py
empire_platform_api_public_client_legacy/api/public_nominations_api.py
empire_platform_api_public_client_legacy/api/reporting_api.py
empire_platform_api_public_client_legacy-7.1.0.dist-info/METADATA
empire_platform_api_public_client_legacy-7.1.0.dist-info/WHEEL
empire_platform_api_public_client_legacy-7.1.0.dist-info/top_level.txt
empire_platform_api_public_client_legacy-7.1.0.dist-info/RECORD
