Metadata-Version: 2.1
Name: empire-platform-api-public-client-legacy
Version: 7.1.0
Summary: Platform API
Home-page: 
Author: BritNed
Author-email: britned.info@britned.com
Keywords: OpenAPI,OpenAPI-Generator,Platform API
Requires-Dist: aenum
Requires-Dist: pydantic (<2,>=1.10.5)
Requires-Dist: python-dateutil
Requires-Dist: urllib3 (<3.0.0,>=1.25.3)
